causalquery/__init__.py
causalquery/graphquery.py
causalquery-0.0.1.dist-info/LICENSE
causalquery-0.0.1.dist-info/METADATA
causalquery-0.0.1.dist-info/WHEEL
causalquery-0.0.1.dist-info/top_level.txt
causalquery-0.0.1.dist-info/RECORD
